dbbrankingparser/__init__.py
dbbrankingparser/cli.py
dbbrankingparser/conversion.py
dbbrankingparser/document.py
dbbrankingparser/httpclient.py
dbbrankingparser/httpserver.py
dbbrankingparser/main.py
dbb_ranking_parser-1.0.0.dist-info/METADATA
dbb_ranking_parser-1.0.0.dist-info/WHEEL
dbb_ranking_parser-1.0.0.dist-info/entry_points.txt
dbb_ranking_parser-1.0.0.dist-info/licenses/LICENSE
dbb_ranking_parser-1.0.0.dist-info/RECORD
