Metadata-Version: 2.4
Name: dbb-ranking-parser
Version: 1.0.0
Summary: Extract league rankings from the DBB (Deutscher Basketball Bund e.V.) website.
Project-URL: Website, https://homework.nwsnet.de/releases/4a51/#dbb-ranking-parser
Project-URL: Repository (GitHub), https://github.com/btb-royals/dbb-ranking-parser
Project-URL: Repository (Sourcehut), https://sr.ht/~homeworkprod/dbb-ranking-parser/
Project-URL: Changelog, https://github.com/btb-royals/dbb-ranking-parser/blob/main/CHANGES.rst
Author-email: Jochen Kupperschmidt <homework@nwsnet.de>
License: MIT
License-File: LICENSE
Keywords: basketball,rankings,scrape
Classifier: Development Status :: 6 - Mature
Classifier: Intended Audience :: Other Audience
Classifier: License :: OSI Approved :: MIT License
Classifier: Operating System :: OS Independent
Classifier: Programming Language :: Python
Classifier: Programming Language :: Python :: 3
Classifier: Programming Language :: Python :: 3.9
Classifier: Programming Language :: Python :: 3.10
Classifier: Programming Language :: Python :: 3.11
Classifier: Programming Language :: Python :: 3.12
Classifier: Programming Language :: Python :: 3.13
Classifier: Topic :: Internet :: WWW/HTTP :: Dynamic Content
Classifier: Topic :: Other/Nonlisted Topic
Requires-Python: >=3.9
Requires-Dist: lxml>=5.3.0
